imghash/__init__.py
imghash/__init__.pyi
imghash/imghash.cpython-310-x86_64-linux-gnu.so
imghash/py.typed
imghash_rs-0.4.0.dist-info/METADATA
imghash_rs-0.4.0.dist-info/WHEEL
imghash_rs-0.4.0.dist-info/licenses/LICENSE
imghash_rs-0.4.0.dist-info/RECORD
