Metadata-Version: 2.4
Name: imghash-rs
Version: 0.4.0
Classifier: Intended Audience :: Developers
Classifier: Programming Language :: Python :: 3
Classifier: Programming Language :: Python :: 3.9
Classifier: Programming Language :: Python :: 3.10
Classifier: Programming Language :: Python :: 3.11
Classifier: Programming Language :: Python :: 3.12
Classifier: Programming Language :: Python :: 3.13
License-File: LICENSE
Summary: Image hashing powered by Rust!
Keywords: image,hashing
Author-email: Yannick Alexander <yannick@alexanderdev.io>
Requires-Python: >=3.9, <3.14
Project-URL: repository, https://github.com/yannickalex07/imghash-py
